exzlogger.py
exzlogger-0.0.2.dist-info/METADATA
exzlogger-0.0.2.dist-info/WHEEL
exzlogger-0.0.2.dist-info/licenses/LICENSE
exzlogger-0.0.2.dist-info/RECORD
