Metadata-Version: 2.1
Name: exzlogger
Version: 0.0.2
Summary: Easily create useful logger.
Project-URL: Homepage, https://github.com/TongRao/exzlogger
Project-URL: Issues, https://github.com/TongRao/exzlogger/issues
Author-email: TongRao <tongrao121@gmail.com>
License-File: LICENSE
Classifier: License :: OSI Approved :: MIT License
Classifier: Operating System :: OS Independent
Classifier: Programming Language :: Python :: 3
Requires-Python: >=3.5
